{
	"name": "CleanSeattlePetLicDatatoSNowflake",
	"properties": {
		"activities": [
			{
				"name": "StageData",
				"type": "ExecuteDataFlow",
				"state": "Inactive",
				"onInactiveMarkAs": "Succeeded",
				"dependsOn": [],
				"policy": {
					"timeout": "0.00:30:00",
					"retry": 0,
					"retryIntervalInSeconds": 30,
					"secureOutput": false,
					"secureInput": false
				},
				"userProperties": [],
				"typeProperties": {
					"dataflow": {
						"referenceName": "SeattlePetLicense_Dataset_dataflow_Cleaning",
						"type": "DataFlowReference",
						"parameters": {
							"Job_ID": {
								"value": "'@{substring(pipeline().RunId, 1,10)}'",
								"type": "Expression"
							}
						}
					},
					"compute": {
						"coreCount": 8,
						"computeType": "General"
					},
					"traceLevel": "Fine"
				}
			},
			{
				"name": "LoadBreedDIM",
				"type": "ExecuteDataFlow",
				"state": "Inactive",
				"onInactiveMarkAs": "Succeeded",
				"dependsOn": [
					{
						"activity": "StageData",
						"dependencyConditions": [
							"Succeeded"
						]
					}
				],
				"policy": {
					"timeout": "0.00:30:00",
					"retry": 0,
					"retryIntervalInSeconds": 30,
					"secureOutput": false,
					"secureInput": false
				},
				"userProperties": [],
				"typeProperties": {
					"dataflow": {
						"referenceName": "df_Load_Breed_DIM",
						"type": "DataFlowReference",
						"parameters": {
							"DI_JOB_ID": {
								"value": "'@{substring(pipeline().RunId, 1,10)}'",
								"type": "Expression"
							}
						}
					},
					"compute": {
						"coreCount": 8,
						"computeType": "General"
					},
					"traceLevel": "Fine"
				}
			},
			{
				"name": "LoadLocationDIM",
				"type": "ExecuteDataFlow",
				"state": "Inactive",
				"onInactiveMarkAs": "Succeeded",
				"dependsOn": [
					{
						"activity": "LoadBreedDIM",
						"dependencyConditions": [
							"Succeeded"
						]
					}
				],
				"policy": {
					"timeout": "0.00:30:00",
					"retry": 0,
					"retryIntervalInSeconds": 30,
					"secureOutput": false,
					"secureInput": false
				},
				"userProperties": [],
				"typeProperties": {
					"dataflow": {
						"referenceName": "df_Location_DIM",
						"type": "DataFlowReference",
						"parameters": {
							"JOB_ID": {
								"value": "'@{substring(pipeline().RunId, 1,10)}'",
								"type": "Expression"
							}
						}
					},
					"compute": {
						"coreCount": 8,
						"computeType": "General"
					},
					"traceLevel": "Fine"
				}
			},
			{
				"name": "LoadPetLicFact",
				"type": "ExecuteDataFlow",
				"dependsOn": [
					{
						"activity": "LoadLocationDIM",
						"dependencyConditions": [
							"Succeeded"
						]
					}
				],
				"policy": {
					"timeout": "0.00:30:00",
					"retry": 0,
					"retryIntervalInSeconds": 30,
					"secureOutput": false,
					"secureInput": false
				},
				"userProperties": [],
				"typeProperties": {
					"dataflow": {
						"referenceName": "df_Pet_LIC_FCT",
						"type": "DataFlowReference",
						"parameters": {
							"JOB_ID": {
								"value": "'@{substring(pipeline().RunId, 1,10)}'",
								"type": "Expression"
							}
						}
					},
					"compute": {
						"coreCount": 8,
						"computeType": "General"
					},
					"traceLevel": "Fine"
				}
			}
		],
		"annotations": []
	}
}